cipetpet/__init__.py
cipetpet/greet.py
cipetpet-0.0.0.0.2.dist-info/METADATA
cipetpet-0.0.0.0.2.dist-info/WHEEL
cipetpet-0.0.0.0.2.dist-info/top_level.txt
cipetpet-0.0.0.0.2.dist-info/RECORD
