Metadata-Version: 2.1
Name: cipetpet
Version: 0.0.0.0.2
Summary: cipetpet cicikus
Home-page: UNKNOWN
Author: tayyip.osman
Author-email: toaydiner@armagroupholding.com
License: UNKNOWN
Keywords: python,cipetpet,cici kus cici kus
Platform: UNKNOWN
Classifier: Development Status :: 3 - Alpha
Classifier: Intended Audience :: Education
Classifier: Programming Language :: Python :: 2
Classifier: Programming Language :: Python :: 3
Classifier: Operating System :: MacOS :: MacOS X
Classifier: Operating System :: Microsoft :: Windows
